jlogin/__init__.py
jlogin/jlogin.py
jlogin/utils/__init__.py
jlogin/utils/jlib.py
jlogin-1.0.0.dist-info/LICENSE
jlogin-1.0.0.dist-info/METADATA
jlogin-1.0.0.dist-info/WHEEL
jlogin-1.0.0.dist-info/entry_points.txt
jlogin-1.0.0.dist-info/top_level.txt
jlogin-1.0.0.dist-info/RECORD
