Metadata-Version: 2.1
Name: jlogin
Version: 1.0.0
Summary: Example system login
Home-page: https://github.com/williamcanin/jlogin
Author: William Canin
Author-email: william.costa.canin@gmail.com
Maintainer: William Canin
License: MIT Licenses
Keywords: example jlogin
Platform: any
Classifier: Programming Language :: Python :: 3
Classifier: License :: OSI Approved :: MIT License
Classifier: Operating System :: MacOS :: MacOS X
Classifier: Operating System :: Microsoft :: Windows
Classifier: Operating System :: POSIX
Classifier: Operating System :: POSIX :: Linux
Requires-Python: >= 3.6
Provides-Extra: dev
Requires-Dist: twine ; extra == 'dev'
